pysleepme/__init__.py
pysleepme/const.py
pysleepme/exceptions.py
pysleepme/py_sleep_me_api/__init__.py
pysleepme/py_sleep_me_api/api/__init__.py
pysleepme/py_sleep_me_api/api/device_control/__init__.py
pysleepme/py_sleep_me_api/api/device_control/get_devices.py
pysleepme/py_sleep_me_api/api/device_control/get_devices_device_id.py
pysleepme/py_sleep_me_api/api/device_control/patch_devices_device_id.py
pysleepme/py_sleep_me_api/client.py
pysleepme/py_sleep_me_api/models/__init__.py
pysleepme/py_sleep_me_api/models/device_list_item.py
pysleepme/py_sleep_me_api/models/dock_pro_control.py
pysleepme/py_sleep_me_api/models/dock_pro_control_display_temperature_unit.py
pysleepme/py_sleep_me_api/models/dock_pro_control_thermal_control_status.py
pysleepme/py_sleep_me_api/models/status.py
pysleepme/py_sleep_me_api/models/status_about.py
pysleepme/py_sleep_me_api/models/status_control.py
pysleepme/py_sleep_me_api/models/status_status.py
pysleepme/py_sleep_me_api/models/status_update_response.py
pysleepme/py_sleep_me_api/py.typed
pysleepme/py_sleep_me_api/types.py
pysleepme/pysleepme.py
pysleepme-0.1.0.dist-info/LICENSE
pysleepme-0.1.0.dist-info/WHEEL
pysleepme-0.1.0.dist-info/METADATA
pysleepme-0.1.0.dist-info/RECORD
